.dockerignore
.gitignore
.gitmodules
.pre-commit-config.yaml
CHANGES.rst
CMakeLists.txt
CODE_OF_CONDUCT.md
CONTRIBUTING.md
Dockerfile
LICENSE
MANIFEST.in
README.md
pyproject.toml
requirements.txt
setup.cfg
setup.py
.github/workflows/conda.yml
.github/workflows/docker-publish.yml
.github/workflows/python-package.yml
.github/workflows/python-publish.yml
.github/workflows/quay-io-publish.yml
.github/workflows/snapcraft.yml
.github/workflows/sphinx.yml
conda/environment.yaml
conda/meta.yaml
docs/.nojekyll
docs/Makefile
docs/make.bat
docs/source/api.rst
docs/source/conf.py
docs/source/configuration.rst
docs/source/index.rst
docs/source/installation.rst
docs/source/publications.rst
docs/source/tutorial.rst
docs/source/usage.rst
docs/source/ext/pydantic_settings.py
docs/source/images/parakeet.png
docs/source/images/parakeet_logo.png
docs/source/images/parakeet_small.png
newsfragments/.gitignore
pybind11/.appveyor.yml
pybind11/.clang-format
pybind11/.clang-tidy
pybind11/.cmake-format.yaml
pybind11/.codespell-ignore-lines
pybind11/.git
pybind11/.gitattributes
pybind11/.gitignore
pybind11/.pre-commit-config.yaml
pybind11/.readthedocs.yml
pybind11/CMakeLists.txt
pybind11/LICENSE
pybind11/MANIFEST.in
pybind11/README.rst
pybind11/SECURITY.md
pybind11/noxfile.py
pybind11/pyproject.toml
pybind11/setup.cfg
pybind11/setup.py
pybind11/.github/CODEOWNERS
pybind11/.github/CONTRIBUTING.md
pybind11/.github/dependabot.yml
pybind11/.github/labeler.yml
pybind11/.github/labeler_merged.yml
pybind11/.github/pull_request_template.md
pybind11/.github/ISSUE_TEMPLATE/bug-report.yml
pybind11/.github/ISSUE_TEMPLATE/config.yml
pybind11/.github/matchers/pylint.json
pybind11/.github/workflows/ci.yml
pybind11/.github/workflows/configure.yml
pybind11/.github/workflows/format.yml
pybind11/.github/workflows/labeler.yml
pybind11/.github/workflows/pip.yml
pybind11/.github/workflows/upstream.yml
pybind11/docs/Doxyfile
pybind11/docs/Makefile
pybind11/docs/basics.rst
pybind11/docs/benchmark.py
src/python_parakeet.egg-info/PKG-INFO
src/python_parakeet.egg-info/SOURCES.txt
src/python_parakeet.egg-info/dependency_links.txt
src/python_parakeet.egg-info/entry_points.txt
src/python_parakeet.egg-info/requires.txt
src/python_parakeet.egg-info/top_level.txt
