Metadata-Version: 2.4
Name: python-parakeet
Version: 0.6.8
Summary: A phantom generator
Home-page: https://github.com/rosalindfranklininstitute/parakeet
Author: James Parkhurst
Author-email: james.parkhurst@diamond.ac.uk
License: GPL v3
Project-URL: Source, https://github.com/rosalindfranklininstitute/parakeet
Project-URL: Tracker, https://github.com/rosalindfranklininstitute/parakeet/issues
Keywords: MULTEM
Platform: unix
Platform: linux
Platform: osx
Platform: cygwin
Platform: win32
Classifier: Development Status :: 4 - Beta
Classifier: Intended Audience :: Developers
Classifier: License :: OSI Approved :: BSD License
Classifier: Operating System :: POSIX
Classifier: Operating System :: Microsoft :: Windows
Classifier: Operating System :: MacOS :: MacOS X
Classifier: Topic :: Utilities
Classifier: Programming Language :: Python :: 3.8
Classifier: Programming Language :: Python :: 3.9
Classifier: Programming Language :: Python :: 3.10
License-File: LICENSE
Requires-Dist: distributed
Requires-Dist: dask_jobqueue
Requires-Dist: gemmi
Requires-Dist: guanaco
Requires-Dist: h5py
Requires-Dist: maptools
Requires-Dist: mrcfile>=1.5.4
Requires-Dist: numpy
Requires-Dist: pandas
Requires-Dist: pillow
Requires-Dist: profet
Requires-Dist: pydantic>=2.0
Requires-Dist: python-multem
Requires-Dist: pyyaml
Requires-Dist: scipy
Requires-Dist: starfile
Requires-Dist: lxml_html_clean
Provides-Extra: build-sphinx
Requires-Dist: sphinx; extra == "build-sphinx"
Requires-Dist: sphinx_rtd_theme; extra == "build-sphinx"
Requires-Dist: sphinx-argparse; extra == "build-sphinx"
Provides-Extra: test
Requires-Dist: pytest; extra == "test"
Requires-Dist: pytest-cov; extra == "test"
Requires-Dist: mock; extra == "test"
Dynamic: license-file
Dynamic: provides-extra
Dynamic: requires-dist
